{"version":1,"resource":"file:///home/moiz/Work/Nafisa-Communication/React-Native/nafisa-communication/src/screens/LoginScreen.tsx","entries":[{"id":"UTRa.tsx","timestamp":1776690632139},{"id":"ZwDx.tsx","timestamp":1776691828663},{"id":"HfBo.tsx","source":"undoRedo.source","timestamp":1776691954931},{"id":"lLQu.tsx","timestamp":1776692208735},{"id":"qCaQ.tsx","timestamp":1776692887855},{"id":"Zssj.tsx","source":"Chat Edit: 'take a look at the reavt native app i am starting to build with nativewind'","timestamp":1776693834930}]}